latexexpr/__init__.py
latexexpr/sympy/__init__.py
latexexpr-0.4.1.dist-info/LICENSE
latexexpr-0.4.1.dist-info/METADATA
latexexpr-0.4.1.dist-info/WHEEL
latexexpr-0.4.1.dist-info/top_level.txt
latexexpr-0.4.1.dist-info/RECORD
